flamapy/metamodels/pysat_diagnosis_metamodel/__init__.py
flamapy/metamodels/pysat_diagnosis_metamodel/models/__init__.py
flamapy/metamodels/pysat_diagnosis_metamodel/models/pysat_diagnosis_model.py
flamapy/metamodels/pysat_diagnosis_metamodel/operations/__init__.py
flamapy/metamodels/pysat_diagnosis_metamodel/operations/pysat_abstract_identifier.py
flamapy/metamodels/pysat_diagnosis_metamodel/operations/pysat_conflict.py
flamapy/metamodels/pysat_diagnosis_metamodel/operations/pysat_diagnosis.py
flamapy/metamodels/pysat_diagnosis_metamodel/operations/diagnosis/__init__.py
flamapy/metamodels/pysat_diagnosis_metamodel/operations/diagnosis/checker.py
flamapy/metamodels/pysat_diagnosis_metamodel/operations/diagnosis/fastdiag.py
flamapy/metamodels/pysat_diagnosis_metamodel/operations/diagnosis/quickxplain.py
flamapy/metamodels/pysat_diagnosis_metamodel/operations/diagnosis/utils.py
flamapy/metamodels/pysat_diagnosis_metamodel/operations/diagnosis/hsdag/__init__.py
flamapy/metamodels/pysat_diagnosis_metamodel/operations/diagnosis/hsdag/hsdag.py
flamapy/metamodels/pysat_diagnosis_metamodel/operations/diagnosis/hsdag/node.py
flamapy/metamodels/pysat_diagnosis_metamodel/operations/diagnosis/hsdag/labeler/__init__.py
flamapy/metamodels/pysat_diagnosis_metamodel/operations/diagnosis/hsdag/labeler/fastdiag_labeler.py
flamapy/metamodels/pysat_diagnosis_metamodel/operations/diagnosis/hsdag/labeler/labeler.py
flamapy/metamodels/pysat_diagnosis_metamodel/operations/diagnosis/hsdag/labeler/quickxplain_labeler.py
flamapy/metamodels/pysat_diagnosis_metamodel/transformations/__init__.py
flamapy/metamodels/pysat_diagnosis_metamodel/transformations/fm_to_diag_pysat.py
flamapy/metamodels/pysat_metamodel/__init__.py
flamapy/metamodels/pysat_metamodel/models/__init__.py
flamapy/metamodels/pysat_metamodel/models/pysat_model.py
flamapy/metamodels/pysat_metamodel/models/txtcnf_model.py
flamapy/metamodels/pysat_metamodel/operations/__init__.py
flamapy_sat-2.0.1.dist-info/METADATA
flamapy_sat-2.0.1.dist-info/WHEEL
flamapy_sat-2.0.1.dist-info/top_level.txt
flamapy_sat-2.0.1.dist-info/RECORD
